pyaww/__init__.py
pyaww/always_on_task.py
pyaww/console.py
pyaww/errors.py
pyaww/file.py
pyaww/sched_task.py
pyaww/static_file.py
pyaww/static_header.py
pyaww/types.py
pyaww/user.py
pyaww/webapp.py
pyaww/utils/__init__.py
pyaww/utils/cache.py
pyaww/utils/helper.py
pyaww-1.0.0.dist-info/LICENSE
pyaww-1.0.0.dist-info/METADATA
pyaww-1.0.0.dist-info/WHEEL
pyaww-1.0.0.dist-info/top_level.txt
pyaww-1.0.0.dist-info/RECORD
