Metadata-Version: 2.1
Name: pyaww
Version: 1.0.0
Summary: An API wrapper around the PythonAnywhere's API.
Home-page: https://github.com/ammarsys/pyaww/
Author: ammarsys
Author-email: amarftw1@gmail.com
License: MIT
Project-URL: Bug Tracker, https://github.com/ammarsys/pyaww/issues
Project-URL: Documentation, https://pyaww-docs.vercel.app/
Platform: UNKNOWN
Classifier: Development Status :: 3 - Alpha
Classifier: Intended Audience :: Developers
Classifier: Topic :: Software Development :: Build Tools
Classifier: License :: OSI Approved :: MIT License
Classifier: Programming Language :: Python :: 3.6
Classifier: Operating System :: OS Independent
Requires-Python: >=3.9
License-File: LICENSE
Requires-Dist: aiohttp (==3.8.1)
